divvy/__init__.py
divvy/__main__.py
divvy/_version.py
divvy/compute.py
divvy/const.py
divvy/utils.py
divvy/default_config/divvy_config.yaml
divvy/default_config/divvy_templates/localhost_bulker_template.sub
divvy/default_config/divvy_templates/localhost_docker_template.sub
divvy/default_config/divvy_templates/localhost_singularity_template.sub
divvy/default_config/divvy_templates/localhost_template.sub
divvy/default_config/divvy_templates/lsf_template.sub
divvy/default_config/divvy_templates/sge_template.sub
divvy/default_config/divvy_templates/slurm_singularity_template.sub
divvy/default_config/divvy_templates/slurm_template.sub
divvy/schemas/divvy_config_schema.yaml
divvy-0.6.0.dist-info/LICENSE.txt
divvy-0.6.0.dist-info/METADATA
divvy-0.6.0.dist-info/WHEEL
divvy-0.6.0.dist-info/entry_points.txt
divvy-0.6.0.dist-info/top_level.txt
divvy-0.6.0.dist-info/RECORD
