Metadata-Version: 2.1
Name: divvy
Version: 0.6.0
Summary: A python-based configuration manager for portable environment configurations
Home-page: https://github.com/pepkit/divvy/
Author: Nathan Sheffield, Vince Reuter, Michal Stolarczyk
Author-email: nathan@code.databio.org, vreuter@virginia.edu, mjs5kd@virginia.edu
License: BSD-2-Clause
Keywords: project,metadata,bioinformatics,sequencing,ngs,workflow
Platform: UNKNOWN
Classifier: Development Status :: 4 - Beta
Classifier: License :: OSI Approved :: BSD License
Classifier: Programming Language :: Python :: 2.7
Classifier: Programming Language :: Python :: 3.5
Classifier: Programming Language :: Python :: 3.6
Classifier: Topic :: System :: Distributed Computing
License-File: LICENSE.txt
Requires-Dist: attmap (>=0.12.9)
Requires-Dist: yacman (>=0.8.1)
Requires-Dist: pyyaml (>=5.1)
Requires-Dist: logmuse (>=0.2.0)
Requires-Dist: ubiquerg (>=0.5.0)
